__init__.py
main.py
prompt_lib_cli-0.1.0.dist-info/licenses/LICENSE
prompt_lib_cli-0.1.0.dist-info/METADATA
prompt_lib_cli-0.1.0.dist-info/WHEEL
prompt_lib_cli-0.1.0.dist-info/entry_points.txt
prompt_lib_cli-0.1.0.dist-info/top_level.txt
prompt_lib_cli-0.1.0.dist-info/RECORD
