Metadata-Version: 2.4
Name: prompt-lib-cli
Version: 0.1.0
Summary: A simple prompt library CLI tool
Author-email: Jackie Han <jackiehank@163.com>
License-Expression: MIT
Project-URL: Homepage, https://github.com/jackiehank/prompt-lib-cli
Project-URL: Repository, https://github.com/jackiehank/prompt-lib-cli.git
Requires-Python: >=3.11
License-File: LICENSE
Requires-Dist: editor>=1.6.6
Requires-Dist: prompt-toolkit>=3.0.52
Requires-Dist: pyperclip>=1.11.0
Dynamic: license-file
